{
  "simulate_id": 420,
  "payload": [
    {
      "userId": "XC210211",
      "name": "张三",
      "location_X": 42.0,
      "location_Y": 25.5,
      "path": [
        {
          "locationX": 41.68,
          "locationY": 22.97,
          "CONFIRMEDAT": "2025-12-12 19:01:52"
        },
        {
          "locationX": 43.909,
          "locationY": 17.504,
          "CONFIRMEDAT": "2025-12-12 19:03:43"
        },
        {
          "locationX": 43.909,
          "locationY": 17.504,
          "CONFIRMEDAT": "2025-12-12 19:03:54"
        },
        {
          "locationX": 41.68,
          "locationY": 15.612,
          "CONFIRMEDAT": "2025-12-12 19:12:46"
        },
        {
          "locationX": 41.68,
          "locationY": 15.612,
          "CONFIRMEDAT": "2025-12-12 19:13:52"
        },
        {
          "locationX": 42.833,
          "locationY": 11.366,
          "CONFIRMEDAT": "2025-12-12 19:14:44"
        },
        {
          "locationX": 39.444,
          "locationY": 19.85,
          "CONFIRMEDAT": "2025-12-12 19:19:40"
        },
        {
          "locationX": 39.444,
          "locationY": 19.458,
          "CONFIRMEDAT": "2025-12-12 19:20:28"
        },
        {
          "locationX": 40.599,
          "locationY": 12.402,
          "CONFIRMEDAT": "2025-12-12 19:26:38"
        },
        {
          "locationX": 41.68,
          "locationY": 10.594,
          "CONFIRMEDAT": "2025-12-12 19:30:01"
        },
        {
          "locationX": 41.68,
          "locationY": 10.594,
          "CONFIRMEDAT": "2025-12-12 19:30:11"
        },
        {
          "locationX": 41.68,
          "locationY": 7.12,
          "CONFIRMEDAT": "2025-12-12 19:30:55"
        },
        {
          "locationX": 41.68,
          "locationY": 7.12,
          "CONFIRMEDAT": "2025-12-12 19:31:30"
        },
        {
          "locationX": 43.909,
          "locationY": 7.468,
          "CONFIRMEDAT": "2025-12-12 19:33:56"
        },
        {
          "locationX": 43.909,
          "locationY": 7.468,
          "CONFIRMEDAT": "2025-12-12 19:34:27"
        },
        {
          "locationX": 42.833,
          "locationY": 14.454,
          "CONFIRMEDAT": "2025-12-12 19:35:26"
        },
        {
          "locationX": 42.833,
          "locationY": 16.77,
          "CONFIRMEDAT": "2025-12-12 19:37:18"
        },
        {
          "locationX": 43.909,
          "locationY": 16.732,
          "CONFIRMEDAT": "2025-12-12 19:38:28"
        },
        {
          "locationX": 43.909,
          "locationY": 17.118,
          "CONFIRMEDAT": "2025-12-12 19:41:08"
        },
        {
          "locationX": 43.909,
          "locationY": 18.662,
          "CONFIRMEDAT": "2025-12-12 19:42:44"
        },
        {
          "locationX": 42.833,
          "locationY": 20.63,
          "CONFIRMEDAT": "2025-12-12 19:44:01"
        },
        {
          "locationX": 42.833,
          "locationY": 20.63,
          "CONFIRMEDAT": "2025-12-12 19:44:52"
        },
        {
          "locationX": 42.833,
          "locationY": 20.63,
          "CONFIRMEDAT": "2025-12-12 19:49:09"
        },
        {
          "locationX": 43.909,
          "locationY": 21.364,
          "CONFIRMEDAT": "2025-12-12 19:55:54"
        },
        {
          "locationX": 43.909,
          "locationY": 21.756,
          "CONFIRMEDAT": "2025-12-12 19:58:58"
        }
      ]
    },
    {
      "userId": "XC210212",
      "name": "王五",
      "location_X": 42.0,
      "location_Y": 25.5,
      "path": [
        {
          "locationX": 39.245,
          "locationY": 31.138,
          "CONFIRMEDAT": "2025-12-12 19:01:14"
        },
        {
          "locationX": 39.245,
          "locationY": 33.638,
          "CONFIRMEDAT": "2025-12-12 19:02:10"
        },
        {
          "locationX": 37.759,
          "locationY": 31.138,
          "CONFIRMEDAT": "2025-12-12 19:03:48"
        },
        {
          "locationX": 55.146,
          "locationY": 17.443,
          "CONFIRMEDAT": "2025-12-12 19:11:52"
        },
        {
          "locationX": 55.146,
          "locationY": 17.443,
          "CONFIRMEDAT": "2025-12-12 19:12:49"
        },
        {
          "locationX": 55.146,
          "locationY": 15.127,
          "CONFIRMEDAT": "2025-12-12 19:13:29"
        },
        {
          "locationX": 55.146,
          "locationY": 12.811,
          "CONFIRMEDAT": "2025-12-12 19:14:50"
        },
        {
          "locationX": 55.146,
          "locationY": 12.811,
          "CONFIRMEDAT": "2025-12-12 19:14:54"
        },
        {
          "locationX": 55.146,
          "locationY": 11.267,
          "CONFIRMEDAT": "2025-12-12 19:16:12"
        },
        {
          "locationX": 55.146,
          "locationY": 11.267,
          "CONFIRMEDAT": "2025-12-12 19:17:33"
        }
      ]
    },
    {
      "userId": "XC220962",
      "name": "李四",
      "location_X": 42.0,
      "location_Y": 25.5,
      "path": [
        {
          "locationX": 55.146,
          "locationY": 9.337,
          "CONFIRMEDAT": "2025-12-12 19:02:10"
        },
        {
          "locationX": 55.146,
          "locationY": 9.337,
          "CONFIRMEDAT": "2025-12-12 19:04:14"
        },
        {
          "locationX": 55.146,
          "locationY": 9.337,
          "CONFIRMEDAT": "2025-12-12 19:08:07"
        },
        {
          "locationX": 45.063,
          "locationY": 21.364,
          "CONFIRMEDAT": "2025-12-12 19:17:02"
        },
        {
          "locationX": 45.063,
          "locationY": 21.364,
          "CONFIRMEDAT": "2025-12-12 19:22:05"
        },
        {
          "locationX": 52.943,
          "locationY": 10.118,
          "CONFIRMEDAT": "2025-12-12 19:26:20"
        },
        {
          "locationX": 52.943,
          "locationY": 10.118,
          "CONFIRMEDAT": "2025-12-12 19:30:33"
        },
        {
          "locationX": 52.943,
          "locationY": 9.732,
          "CONFIRMEDAT": "2025-12-12 19:30:47"
        },
        {
          "locationX": 52.943,
          "locationY": 9.732,
          "CONFIRMEDAT": "2025-12-12 19:33:12"
        }
      ]
    },
    {
      "userId": "XC241596",
      "name": "周春花",
      "location_X": 42.0,
      "location_Y": 25.5,
      "path": [
        {
          "locationX": 50.864,
          "locationY": 21.771,
          "CONFIRMEDAT": "2025-12-12 19:00:34"
        },
        {
          "locationX": 50.864,
          "locationY": 20.613,
          "CONFIRMEDAT": "2025-12-12 19:02:16"
        },
        {
          "locationX": 50.864,
          "locationY": 20.613,
          "CONFIRMEDAT": "2025-12-12 19:02:26"
        },
        {
          "locationX": 50.864,
          "locationY": 19.455,
          "CONFIRMEDAT": "2025-12-12 19:05:29"
        },
        {
          "locationX": 51.889,
          "locationY": 18.61,
          "CONFIRMEDAT": "2025-12-12 19:08:04"
        },
        {
          "locationX": 51.889,
          "locationY": 17.452,
          "CONFIRMEDAT": "2025-12-12 19:08:57"
        },
        {
          "locationX": 50.864,
          "locationY": 14.437,
          "CONFIRMEDAT": "2025-12-12 19:09:32"
        },
        {
          "locationX": 50.864,
          "locationY": 14.051,
          "CONFIRMEDAT": "2025-12-12 19:11:07"
        },
        {
          "locationX": 50.864,
          "locationY": 13.665,
          "CONFIRMEDAT": "2025-12-12 19:13:05"
        },
        {
          "locationX": 50.864,
          "locationY": 13.665,
          "CONFIRMEDAT": "2025-12-12 19:14:13"
        },
        {
          "locationX": 51.889,
          "locationY": 13.206,
          "CONFIRMEDAT": "2025-12-12 19:17:14"
        },
        {
          "locationX": 50.864,
          "locationY": 13.279,
          "CONFIRMEDAT": "2025-12-12 19:20:08"
        },
        {
          "locationX": 40.653,
          "locationY": 3.051,
          "CONFIRMEDAT": "2025-12-12 19:23:45"
        },
        {
          "locationX": 44.136,
          "locationY": 3.051,
          "CONFIRMEDAT": "2025-12-12 19:27:49"
        },
        {
          "locationX": 44.136,
          "locationY": 3.051,
          "CONFIRMEDAT": "2025-12-12 19:31:17"
        },
        {
          "locationX": 48.636,
          "locationY": 20.589,
          "CONFIRMEDAT": "2025-12-12 19:37:28"
        },
        {
          "locationX": 48.636,
          "locationY": 20.975,
          "CONFIRMEDAT": "2025-12-12 19:38:10"
        },
        {
          "locationX": 48.636,
          "locationY": 17.501,
          "CONFIRMEDAT": "2025-12-12 19:39:12"
        },
        {
          "locationX": 40.653,
          "locationY": 3.051,
          "CONFIRMEDAT": "2025-12-12 19:40:45"
        },
        {
          "locationX": 51.889,
          "locationY": 13.592,
          "CONFIRMEDAT": "2025-12-12 19:43:56"
        },
        {
          "locationX": 49.65,
          "locationY": 21.385,
          "CONFIRMEDAT": "2025-12-12 19:46:34"
        },
        {
          "locationX": 49.65,
          "locationY": 21.385,
          "CONFIRMEDAT": "2025-12-12 19:47:01"
        },
        {
          "locationX": 51.889,
          "locationY": 17.066,
          "CONFIRMEDAT": "2025-12-12 19:49:28"
        },
        {
          "locationX": 51.889,
          "locationY": 17.066,
          "CONFIRMEDAT": "2025-12-12 19:50:38"
        },
        {
          "locationX": 51.889,
          "locationY": 16.68,
          "CONFIRMEDAT": "2025-12-12 19:50:58"
        },
        {
          "locationX": 51.889,
          "locationY": 16.68,
          "CONFIRMEDAT": "2025-12-12 19:51:03"
        },
        {
          "locationX": 51.889,
          "locationY": 16.68,
          "CONFIRMEDAT": "2025-12-12 19:51:40"
        },
        {
          "locationX": 51.889,
          "locationY": 16.68,
          "CONFIRMEDAT": "2025-12-12 19:52:03"
        },
        {
          "locationX": 51.889,
          "locationY": 16.68,
          "CONFIRMEDAT": "2025-12-12 19:53:51"
        },
        {
          "locationX": 51.889,
          "locationY": 16.294,
          "CONFIRMEDAT": "2025-12-12 19:55:10"
        },
        {
          "locationX": 51.889,
          "locationY": 16.294,
          "CONFIRMEDAT": "2025-12-12 19:55:28"
        },
        {
          "locationX": 50.864,
          "locationY": 14.823,
          "CONFIRMEDAT": "2025-12-12 19:56:44"
        },
        {
          "locationX": 50.864,
          "locationY": 14.823,
          "CONFIRMEDAT": "2025-12-12 19:56:50"
        },
        {
          "locationX": 50.864,
          "locationY": 10.577,
          "CONFIRMEDAT": "2025-12-12 19:58:40"
        },
        {
          "locationX": 50.864,
          "locationY": 10.577,
          "CONFIRMEDAT": "2025-12-12 19:59:59"
        }
      ]
    }
  ]
}